_pyEMLearn/__init__.py
_pyEMLearn/core.py
_pyEMLearn/layers.py
_pyEMLearn/materials.py
_pyEMLearn/utils.py
_pyEMLearn/catalog/__init__.py
_pyEMLearn/catalog/dielectrics.py
_pyEMLearn/catalog/metals.py
_pyEMLearn/catalog/special.py
pyEMLearn/__init__.py
pyEMLearn/core.py
pyEMLearn/geometry.py
pyEMLearn/layers.py
pyEMLearn/materials.py
pyEMLearn/catalog/__init__.py
pyEMLearn/catalog/dielectrics.py
pyEMLearn/catalog/metals.py
pyEMLearn/catalog/special.py
pyEMLearn-0.2.0.dist-info/LICENSE
pyEMLearn-0.2.0.dist-info/METADATA
pyEMLearn-0.2.0.dist-info/WHEEL
pyEMLearn-0.2.0.dist-info/top_level.txt
pyEMLearn-0.2.0.dist-info/RECORD
