Metadata-Version: 2.1
Name: pyEMLearn
Version: 0.2.0
Summary: A computational E&M package for learning the fundimentals
Home-page: https://github.com/jonathanvanschenck/pyEMLearn
Author: Jonathan D B Van Schenck
Author-email: vanschej@oregonstate.edu
License: UNKNOWN
Platform: UNKNOWN
Classifier: Programming Language :: Python :: 3
Classifier: License :: OSI Approved :: MIT License
Classifier: Operating System :: OS Independent
Requires-Python: >=3.6
Requires-Dist: numpy (>=1.18.4)
